octo_pipeline_python/backends/setuptools/__init__.py
octo_pipeline_python/backends/setuptools/setuptools_backend.py
octo_pipeline_python/backends/setuptools/actions/__init__.py
octo_pipeline_python/backends/setuptools/actions/setuptools_package.py
octo_pipeline_python/backends/setuptools/models/__init__.py
octo_pipeline_python/backends/setuptools/models/setuptools_model.py
octo_pipeline_backend_setuptools_python-1.3.2.dist-info/LICENSE.txt
octo_pipeline_backend_setuptools_python-1.3.2.dist-info/METADATA
octo_pipeline_backend_setuptools_python-1.3.2.dist-info/README.md
octo_pipeline_backend_setuptools_python-1.3.2.dist-info/WHEEL
octo_pipeline_backend_setuptools_python-1.3.2.dist-info/top_level.txt
octo_pipeline_backend_setuptools_python-1.3.2.dist-info/RECORD
